[{"s": "lav-81014-lodochnyj-pritsep", "t": "Прицеп LAV 81014 для лодок: характеристики, отзывы, выбор и ТО", "i": "🎣", "c": "tyuning-i-aksessuary"}, {"s": "lada-podvodnaya-lodka", "t": "Лада подводная лодка: миф или реальность? Технические особенности и правда о проекте", "i": "🌊", "c": "podvodnye-lodki"}, {"s": "ladoga-2-motornaya", "t": "Ладога 2 моторная: характеристики, чертежи и обшивка лодки", "i": "⚓", "c": "metallicheskie-lodki"}, {"s": "lajfkhaki-dlya-lodki-pvkh", "t": "Лайфхаки для лодки ПВХ: продли жизнь плавсредству", "i": "🛶", "c": "lodki-pvkh"}, {"s": "lafet-dlya-lodki-pvkh", "t": "Лафет для лодки ПВХ: выбор, чертежи и правила эксплуатации", "i": "🛶", "c": "lodki-pvkh"}, {"s": "ladoga-1-lodka", "t": "Лодка Ладога 1: обзор, характеристики и отзывы", "i": "⚓", "c": "metallicheskie-lodki"}, {"s": "lajvel-v-lodku-svoimi-rukami", "t": "Лайвел в лодку своими руками: чертежи и инструкции", "i": "🛠️", "c": "sdelaj-sam"}, {"s": "las-5m-3-lodka", "t": "Лодка ЛАС 5М: обзор, характеристики и выбор 3-метрового катамарана", "i": "⚓", "c": "metallicheskie-lodki"}, {"s": "ladozhskie-shkhery-na-lodke", "t": "Ладожские шхеры на лодке: маршрут, карта и секреты", "i": "🛶", "c": "lodki-pvkh"}, {"s": "lafet-dlya-lodki", "t": "Лафет для лодки: виды, чертежи, изготовление своими руками", "i": "🎣", "c": "tyuning-i-aksessuary"}, {"s": "laker-410-kharakteristiki-lodka", "t": "Лодка Лакер 410: характеристики, отзывы и особенности", "i": "🛶", "c": "lodki-pvkh"}, {"s": "lafet-dlya-lodki-svoimi-rukami", "t": "Лафет для лодки своими руками: чертежи, материалы и сборка", "i": "🛠️", "c": "sdelaj-sam"}, {"s": "lav-81015-pritsep-lodochnyj", "t": "Лав 81015 прицеп лодочный: характеристики, фото, отзывы", "i": "🎣", "c": "tyuning-i-aksessuary"}, {"s": "ladoga-2-motornaya-lodka-kharakteristiki", "t": "Ладога 2: полные характеристики, размеры и отзывы владельцев", "i": "⚓", "c": "metallicheskie-lodki"}, {"s": "las-1-lodka-aviatsionnaya-spasatelnaya-kupit", "t": "ЛАС-1: купить авиационную спасательную лодку для выживания", "i": "🛶", "c": "lodki-pvkh"}, {"s": "ladoga-2-motornaya-lodka-kupit", "t": "Лодка Ладога 2: где купить, цена, характеристики и отзывы", "i": "⚓", "c": "metallicheskie-lodki"}, {"s": "las-5m-3-lodka-aviatsionnaya-spasatelnaya-pyatimestnaya", "t": "ЛАС-5М-3: Обзор авиационной спасательной лодки", "i": "📁", "c": null}, {"s": "lada-niva-s-novym-dvigatelem", "t": "Лада Нива с новым двигателем: характеристики, планы и реальность", "i": "📁", "c": "drugoe"}, {"s": "latka-dlya-lodki", "t": "Как клеить латку на лодку ПВХ: пошаговая инструкция и советы", "i": "🔧", "c": "remont-i-to"}, {"s": "lajvel-v-lodku-kupit", "t": "Лайвел в лодку купить: ТОП моделей и советы по установке", "i": "🛶", "c": "lodki-pvkh"}, {"s": "latka-dlya-lodki-pvkh", "t": "Латка для лодки ПВХ: выбор клея и инструкция по ремонту", "i": "🔧", "c": "remont-i-to"}]