[{"s": "ozon-lodka-pvkh-pod-motor", "t": "Лодки ПВХ Озон под мотор: как выбрать и эксплуатировать", "i": "🛶", "c": "lodki-pvkh"}, {"s": "ozon-lodki-pvkh-dlya-rybalki", "t": "Лодки ПВХ для рыбалки на Озон: рейтинг лучших моделей и советы", "i": "🛶", "c": "lodki-pvkh"}, {"s": "ozon-lodki-pvkh-pod-motor", "t": "Озон лодки ПВХ под мотор: гид по выбору и покупке", "i": "🛶", "c": "lodki-pvkh"}, {"s": "ozon-kupit-lodku-pvkh-pod-motor", "t": "Купить лодку ПВХ под мотор на Озон: рейтинг лучших моделей", "i": "🛶", "c": "lodki-pvkh"}, {"s": "ozon-naduvnaya-lodka", "t": "Надувная лодка на Ozon: выбор, отзывы и характеристики", "i": "🛶", "c": "lodki-pvkh"}]